ciphers/__init__.py
ciphers/ciphers.py
ciphers-module/__init__.py
ciphers-module/ciphers.py
ciphers_module/__init__.py
ciphers_module/ciphers.py
ciphers_module/ciphers_module.py
ciphers_module-2.0.2.dist-info/METADATA
ciphers_module-2.0.2.dist-info/WHEEL
ciphers_module-2.0.2.dist-info/top_level.txt
ciphers_module-2.0.2.dist-info/RECORD
