Metadata-Version: 2.1
Name: ciphers_module
Version: 2.0.2
Author: Avyukt27
Author-email: <avyukt.aggarwal007@gmail.com>
Keywords: python,cipher,encode,encrypt,decrypt,decode
